CHANGES
HelloGrok.py
LICENSE
MANIFEST.in
README-pypi.rst
README.md
setup.py
grokpy/__init__.py
grokpy/action.py
grokpy/client.py
grokpy/connection.py
grokpy/data_source_field.py
grokpy/enum.py
grokpy/events_data_source.py
grokpy/exceptions.py
grokpy/local_data_source.py
grokpy/model.py
grokpy/model_specification.py
grokpy/project.py
grokpy/stocks_data_source.py
grokpy/stream.py
grokpy/stream_specification.py
grokpy/swarm.py
grokpy/user.py
grokpy/version.py
grokpy.egg-info/PKG-INFO
grokpy.egg-info/SOURCES.txt
grokpy.egg-info/dependency_links.txt
grokpy.egg-info/requires.txt
grokpy.egg-info/top_level.txt