Metadata-Version: 1.0
Name: grokpy
Version: 0.2.17
Summary: Python client for Grok Prediction Service
Home-page: http://github.com/numenta/grok-py
Author: Austin Marshall
Author-email: amarshall@groksolutions.com
License: MIT
Download-URL: https://pypi.python.org/packages/source/g/grokpy/grokpy-0.2.17.tar.gz
Keywords: groksolutions,numenta,prediction
Platform: UNKNOWN
Classifier: Development Status :: 1 - Planning
Classifier: Environment :: Console
Classifier: Intended Audience :: Developers
Classifier: License :: OSI Approved :: MIT License
Classifier: Natural Language :: English
Classifier: Operating System :: OS Independent
Classifier: Programming Language :: Python
